adcustom/__init__.py
adcustom-0.0.4.dist-info/licenses/LICENSE
adcustom-0.0.4.dist-info/METADATA
adcustom-0.0.4.dist-info/WHEEL
adcustom-0.0.4.dist-info/top_level.txt
adcustom-0.0.4.dist-info/RECORD
