Metadata-Version: 2.4
Name: adcustom
Version: 0.0.4
Summary: A custom Python module containing various mathematical, string, and matrix operations.
Author-email: Amit Dutta <amitdutta4255@gmail.com>
Project-URL: Github, https://github.com/notamitgamer
Keywords: mathematics,matrix,string,utility,prime,factorial,permutation,combination,mean,median,mode
Classifier: Programming Language :: Python :: 3
Classifier: License :: OSI Approved :: MIT License
Classifier: Operating System :: OS Independent
Classifier: Development Status :: 3 - Alpha
Classifier: Topic :: Scientific/Engineering :: Mathematics
Classifier: Topic :: Utilities
Requires-Python: >=3.9
License-File: LICENSE
Dynamic: license-file
